{
    "title":"함벽루",
    "location":"경상남도 합천군",
    "source":"ham_byuck_roo",
    "content":"<span>涵碧樓</span>",
    "translate":".",
    "information":"우암이 청년시절 동춘당과 함께 영남지방을 유람한 적은 있지만, 출사하고 난 이후에는 급변하는 정세의 한가운데 있다 보니 유배를 떠나지 않는 한 한가롭게 유람을 다닐 여유는 없어 방문 기념 삼아 글씨를 남기 사례는 없는 것 같다. 후대에 들어와 영남에도 우암의 학문을 추종하는 노론세력이 적지 않았지만 우암의 글씨로 현판을 달거나 각자를 새겨 널리 보이기엔 쉽지 않았던지 전국적으로 그 많던 우암의 글씨가 영남지역에서는 아주 귀하다.</p><p class='article'>우암의 큼지막한 글씨 ‘<span>涵碧樓</span>(함벽루)’가 합천 황강변 함벽루 뒤 석벽에 새겨져 있고, 좌측 관지에 ‘<span>尤庵書</span>(우암서)’라 써 놓았다. 우측에 새겨진 명문도 우암의 글씨인데, <span>崇禎後辛酉</span>인 1681년에 함벽루를 중건한 기념으로 당시 군수 조지항(<span>趙持恒</span>)에게 써준 글씨임을 알 수 있다.</p><p class='article'>우암이 함경도로 유배되었다가 거제로 이배된 후에 1680년 단성을 거쳐 합천으로 가는 도중에 해배가 되었다. 그래서, 그 이듬해인 1681년에 합천에 머물면서 글씨를 써준 것은 아닐까 추측해본다."
}